README.md
setup.py
sarf_zeromq_bridge/__init__.py
sarf_zeromq_bridge/zeromq_bridge.py
sarf_zeromq_bridge.egg-info/PKG-INFO
sarf_zeromq_bridge.egg-info/SOURCES.txt
sarf_zeromq_bridge.egg-info/dependency_links.txt
sarf_zeromq_bridge.egg-info/entry_points.txt
sarf_zeromq_bridge.egg-info/requires.txt
sarf_zeromq_bridge.egg-info/top_level.txt