Metadata-Version: 2.1
Name: sarf-zeromq-bridge
Version: 0.1.0
Summary: Bridge between SARF messages and zeroMQ protocol
Home-page: UNKNOWN
Author: Samuel López Saura
Author-email: samuellopezsaura@gmail.com
License: MIT
Platform: UNKNOWN
Classifier: Programming Language :: Python :: 3
Classifier: License :: OSI Approved :: MIT License
Classifier: Operating System :: OS Independent
